nac_test_pyats_common/__init__.py
nac_test_pyats_common/py.typed
nac_test_pyats_common/aci/__init__.py
nac_test_pyats_common/aci/auth.py
nac_test_pyats_common/aci/test_base.py
nac_test_pyats_common/catc/__init__.py
nac_test_pyats_common/catc/auth.py
nac_test_pyats_common/catc/test_base.py
nac_test_pyats_common/common/__init__.py
nac_test_pyats_common/common/base_device_resolver.py
nac_test_pyats_common/iosxe/__init__.py
nac_test_pyats_common/iosxe/catc_resolver.py
nac_test_pyats_common/iosxe/iosxe_resolver.py
nac_test_pyats_common/iosxe/registry.py
nac_test_pyats_common/iosxe/test_base.py
nac_test_pyats_common/sdwan/__init__.py
nac_test_pyats_common/sdwan/api_test_base.py
nac_test_pyats_common/sdwan/auth.py
nac_test_pyats_common/sdwan/device_resolver.py
nac_test_pyats_common/sdwan/ssh_test_base.py
nac_test_pyats_common-0.1.1.dist-info/METADATA
nac_test_pyats_common-0.1.1.dist-info/WHEEL
nac_test_pyats_common-0.1.1.dist-info/licenses/LICENSE
nac_test_pyats_common-0.1.1.dist-info/RECORD
