Metadata-Version: 2.4
Name: nac-test-pyats-common
Version: 0.1.1
Summary: Architecture adapters for Network as Code (NaC) PyATS testing - auth classes, test base classes, and device resolvers
Project-URL: Homepage, https://github.com/netascode/nac-test-pyats-common
Project-URL: Documentation, https://github.com/netascode/nac-test-pyats-common
Project-URL: Repository, https://github.com/netascode/nac-test-pyats-common
Project-URL: Issues, https://github.com/netascode/nac-test-pyats-common/issues
Author-email: Andrea Testino <atestini@cisco.com>
Maintainer-email: Andrea Testino <atestini@cisco.com>
License: MPL-2.0
License-File: LICENSE
Keywords: aci,catalyst-center,cisco,nac,network,pyats,sdwan,testing
Classifier: Development Status :: 4 - Beta
Classifier: Intended Audience :: Developers
Classifier: License :: OSI Approved :: Mozilla Public License 2.0 (MPL 2.0)
Classifier: Operating System :: OS Independent
Classifier: Programming Language :: Python :: 3
Classifier: Programming Language :: Python :: 3.10
Classifier: Programming Language :: Python :: 3.11
Classifier: Programming Language :: Python :: 3.12
Classifier: Programming Language :: Python :: 3.13
Classifier: Topic :: Software Development :: Testing
Classifier: Topic :: System :: Networking
Requires-Python: >=3.10
Requires-Dist: httpx>=0.28
Requires-Dist: nac-test==1.1.0b2
Provides-Extra: dev
Requires-Dist: bandit[toml]>=1.8.6; extra == 'dev'
Requires-Dist: mypy>=1.10; extra == 'dev'
Requires-Dist: pre-commit>=3.0; extra == 'dev'
Requires-Dist: pytest-asyncio>=0.23; extra == 'dev'
Requires-Dist: pytest-cov>=4.0; extra == 'dev'
Requires-Dist: pytest-mock>=3.14; extra == 'dev'
Requires-Dist: pytest>=8.0; extra == 'dev'
Requires-Dist: respx>=0.21; extra == 'dev'
Requires-Dist: ruff>=0.4; extra == 'dev'
